j2toon/__init__.py
j2toon/cli.py
j2toon/decoder.py
j2toon/encoder.py
j2toon-0.1.1.dist-info/licenses/LICENSE
j2toon-0.1.1.dist-info/METADATA
j2toon-0.1.1.dist-info/WHEEL
j2toon-0.1.1.dist-info/entry_points.txt
j2toon-0.1.1.dist-info/top_level.txt
j2toon-0.1.1.dist-info/RECORD
