Metadata-Version: 2.4
Name: j2toon
Version: 0.1.1
Summary: Python helpers to convert between JSON-compatible data and TOON.
Author-email: Vishnu Prasad <vishnuprasadapp@gmail.com>
License-Expression: MIT
Project-URL: Homepage, https://github.com/VishApp/j2toon
Project-URL: Repository, https://github.com/VishApp/j2toon
Project-URL: Documentation, https://github.com/VishApp/j2toon#readme
Requires-Python: >=3.9
License-File: LICENSE
Dynamic: license-file
